geographer/__init__.py
geographer/add_drop_rasters_mixin.py
geographer/add_drop_vectors_mixin.py
geographer/connector.py
geographer/creator_from_source_dataset_base.py
geographer/errors.py
geographer/global_constants.py
geographer/raster_bands_getter_mixin.py
geographer/base_model_dict_conversion/base_model_dict_conversion_functional.py
geographer/base_model_dict_conversion/save_load_base_model_mixin.py
geographer/converters/__init__.py
geographer/converters/combine_remove_vector_classes.py
geographer/converters/label_type_soft_to_categorical.py
geographer/converters/tif_to_npy.py
geographer/cutters/__init__.py
geographer/cutters/cut_every_raster_to_grid.py
geographer/cutters/cut_iter_over_rasters.py
geographer/cutters/cut_iter_over_vectors.py
geographer/cutters/cut_rasters_around_every_vector.py
geographer/cutters/raster_filter_predicates.py
geographer/cutters/raster_selectors.py
geographer/cutters/single_raster_cutter_around_vector.py
geographer/cutters/single_raster_cutter_base.py
geographer/cutters/single_raster_cutter_bbox.py
geographer/cutters/single_raster_cutter_grid.py
geographer/cutters/type_aliases.py
geographer/cutters/vector_filter_predicates.py
geographer/downloaders/__init__.py
geographer/downloaders/base_download_processor.py
geographer/downloaders/base_downloader_for_single_vector.py
geographer/downloaders/downloader_for_vectors.py
geographer/downloaders/eodag_downloader_for_single_vector.py
geographer/downloaders/jaxa_download_processor.py
geographer/downloaders/jaxa_downloader_for_single_vector.py
geographer/downloaders/sentinel2_download_processor.py
geographer/downloaders/sentinel2_safe_unpacking.py
geographer/graph/__init__.py
geographer/graph/bipartite_graph.py
geographer/graph/bipartite_graph_class.py
geographer/graph/bipartite_graph_mixin.py
geographer/graph/type_aliases.py
geographer/label_makers/__init__.py
geographer/label_makers/label_maker_base.py
geographer/label_makers/label_type_conversion_utils.py
geographer-1.0.0.dist-info/LICENSE
geographer-1.0.0.dist-info/METADATA
geographer-1.0.0.dist-info/WHEEL
geographer-1.0.0.dist-info/top_level.txt
geographer-1.0.0.dist-info/RECORD
