Metadata-Version: 2.2
Name: geographer
Version: 1.0.0
Summary: Build object-centric remote sensing computer vision datasets
Author-email: Rustam Antia <rustam.antia@gmail.com>
License: HIPPOCRATIC LICENSE
Keywords: remote sensing,computer vision,satellite imagery,GIS,machine learning
Classifier: License :: Other/Proprietary License
Classifier: Programming Language :: Python :: 3
Requires-Python: >=3.9
License-File: LICENSE
Requires-Dist: eodag
Requires-Dist: eval_type_backport
Requires-Dist: fiona
Requires-Dist: geojson
Requires-Dist: geopandas
Requires-Dist: GitPython
Requires-Dist: ipywidgets
Requires-Dist: networkx
Requires-Dist: numpy
Requires-Dist: packaging
Requires-Dist: pandas
Requires-Dist: pydantic>=2.0
Requires-Dist: pyproj
Requires-Dist: rasterio
Requires-Dist: requests
Requires-Dist: rioxarray
Requires-Dist: rtree
Requires-Dist: scipy
Requires-Dist: sentinelsat
Requires-Dist: Shapely
Requires-Dist: tqdm
Requires-Dist: urllib3
Provides-Extra: dev
Requires-Dist: ruff==0.7.4; extra == "dev"
Requires-Dist: build; extra == "dev"
Requires-Dist: docformatter; extra == "dev"
Requires-Dist: ipykernel; extra == "dev"
Requires-Dist: pytest; extra == "dev"
Provides-Extra: docs
Requires-Dist: furo; extra == "docs"
Requires-Dist: autodoc_pydantic; extra == "docs"
Requires-Dist: docutils; extra == "docs"
Requires-Dist: pandoc; extra == "docs"
Requires-Dist: Sphinx; extra == "docs"
Requires-Dist: sphinx-autodoc-typehints; extra == "docs"
Requires-Dist: nbsphinx; extra == "docs"
Requires-Dist: nbsphinx-link; extra == "docs"
